{
  "id": "weighted-bridge-lift",
  "name": "Weighted Bridge Lift",
  "type": "weights",
  "muscles": ["glutes", "hamstrings", "core"],
  "equipment": ["bodyweight", "dumbbell", "kettlebell"],
  "tags": ["core", "floor", "glutes", "circuit", "on-back", "legs", "bridge-variation"],
  "difficulty": "advanced",
  "duration": 60,
  "description": "Lie on your back with knees bent and feet flat. Hold a dumbbell or kettlebell on your hips. Lift hips into a bridge position, then raise one leg straight up while holding the weight steady. Alternate legs with control."
}
