{
  "id": "wide-grip-push-up",
  "name": "Wide-Grip Push-up",
  "category": "chest",
  "type": "calisthenics",
  "muscles": [
    "chest",
    "shoulders",
    "triceps",
    "core"
  ],
  "equipment": [
    "bodyweight"
  ],
  "tags": [
    "compound",
    "push",
    "upper-body",
    "push-up-variation",
    "floor",
    "on-hands"
  ],
  "difficulty": "beginner",
  "duration": 60,
  "description": "Perform a push-up with hands placed wider than shoulder-width apart. Lower body while keeping arms angled outward, then push back up. This variation emphasizes the outer chest and shoulders.",
  "media": []
}
